azure_keyvault_stuff.py
azure_keyvault_stuff-0.0.5.dist-info/LICENSE
azure_keyvault_stuff-0.0.5.dist-info/METADATA
azure_keyvault_stuff-0.0.5.dist-info/WHEEL
azure_keyvault_stuff-0.0.5.dist-info/top_level.txt
azure_keyvault_stuff-0.0.5.dist-info/RECORD
