Metadata-Version: 2.1
Name: azure-keyvault-stuff
Version: 0.0.5
Summary: Azure Key Vault Helper Package
Home-page: https://github.com/george-oconnor/azure-keyvault-stuff
Author: george.oconnor (George O' Connor)
Author-email: <george@georgestools.com>
Keywords: python,azure,keyvault,helper,secret,secrets,client,get,set,delete,vault,value,values,credential,credentials
Classifier: Development Status :: 3 - Alpha
Classifier: Intended Audience :: Developers
Classifier: Programming Language :: Python :: 3
Classifier: Operating System :: OS Independent
Classifier: License :: OSI Approved :: MIT License
License-File: LICENSE
Requires-Dist: azure-keyvault-secrets
